outerbounds/__init__.py
outerbounds/_vendor/PyYAML.LICENSE
outerbounds/_vendor/__init__.py
outerbounds/_vendor/_yaml/__init__.py
outerbounds/_vendor/click/__init__.py
outerbounds/_vendor/click/_compat.py
outerbounds/_vendor/click/_termui_impl.py
outerbounds/_vendor/click/_textwrap.py
outerbounds/_vendor/click/_winconsole.py
outerbounds/_vendor/click/core.py
outerbounds/_vendor/click/decorators.py
outerbounds/_vendor/click/exceptions.py
outerbounds/_vendor/click/formatting.py
outerbounds/_vendor/click/globals.py
outerbounds/_vendor/click/parser.py
outerbounds/_vendor/click/py.typed
outerbounds/_vendor/click/shell_completion.py
outerbounds/_vendor/click/termui.py
outerbounds/_vendor/click/testing.py
outerbounds/_vendor/click/types.py
outerbounds/_vendor/click/utils.py
outerbounds/_vendor/click.LICENSE
outerbounds/_vendor/vendor_any.txt
outerbounds/_vendor/yaml/__init__.py
outerbounds/_vendor/yaml/_yaml.cpython-311-darwin.so
outerbounds/_vendor/yaml/composer.py
outerbounds/_vendor/yaml/constructor.py
outerbounds/_vendor/yaml/cyaml.py
outerbounds/_vendor/yaml/dumper.py
outerbounds/_vendor/yaml/emitter.py
outerbounds/_vendor/yaml/error.py
outerbounds/_vendor/yaml/events.py
outerbounds/_vendor/yaml/loader.py
outerbounds/_vendor/yaml/nodes.py
outerbounds/_vendor/yaml/parser.py
outerbounds/_vendor/yaml/reader.py
outerbounds/_vendor/yaml/representer.py
outerbounds/_vendor/yaml/resolver.py
outerbounds/_vendor/yaml/scanner.py
outerbounds/_vendor/yaml/serializer.py
outerbounds/_vendor/yaml/tokens.py
outerbounds/apps/__init__.py
outerbounds/apps/cli.py
outerbounds/cli_main.py
outerbounds/command_groups/__init__.py
outerbounds/command_groups/apps_cli.py
outerbounds/command_groups/cli.py
outerbounds/command_groups/fast_bakery_cli.py
outerbounds/command_groups/flowprojects_cli.py
outerbounds/command_groups/integrations_cli.py
outerbounds/command_groups/kubernetes_cli.py
outerbounds/command_groups/local_setup_cli.py
outerbounds/command_groups/perimeters_cli.py
outerbounds-0.11.2.dist-info/METADATA
outerbounds-0.11.2.dist-info/WHEEL
outerbounds-0.11.2.dist-info/entry_points.txt
outerbounds-0.11.2.dist-info/RECORD
