Metadata-Version: 2.1
Name: outerbounds
Version: 0.11.2
Summary: More Data Science, Less Administration
License: Proprietary
Keywords: data science,machine learning,MLOps
Author: Outerbounds, Inc.
Requires-Python: >=3.7,<4.0
Classifier: Development Status :: 4 - Beta
Classifier: License :: Other/Proprietary License
Classifier: Programming Language :: Python :: 3
Classifier: Programming Language :: Python :: 3.7
Classifier: Programming Language :: Python :: 3.8
Classifier: Programming Language :: Python :: 3.9
Classifier: Programming Language :: Python :: 3.10
Classifier: Programming Language :: Python :: 3.11
Classifier: Programming Language :: Python :: 3.12
Provides-Extra: azure
Provides-Extra: gcp
Provides-Extra: otel
Provides-Extra: snowflake
Requires-Dist: azure-identity (>=1.15.0,<2.0.0) ; extra == "azure"
Requires-Dist: azure-keyvault-secrets (>=4.7.0,<5.0.0) ; extra == "azure"
Requires-Dist: azure-storage-blob (>=12.9.0,<13.0.0) ; extra == "azure"
Requires-Dist: boto3
Requires-Dist: google-api-core (>=2.16.1,<3.0.0) ; extra == "gcp"
Requires-Dist: google-auth (>=2.27.0,<3.0.0) ; extra == "gcp"
Requires-Dist: google-cloud-secret-manager (>=2.20.0,<3.0.0) ; extra == "gcp"
Requires-Dist: google-cloud-storage (>=2.14.0,<3.0.0) ; extra == "gcp"
Requires-Dist: metaflow_checkpoint (==0.2.10)
Requires-Dist: ob-metaflow (==2.19.15.3)
Requires-Dist: ob-metaflow-extensions (==1.5.0)
Requires-Dist: ob-metaflow-stubs (==6.0.11.2)
Requires-Dist: ob-project-utils (>=0.2.14)
Requires-Dist: opentelemetry-distro (>=0.41b0) ; extra == "otel"
Requires-Dist: opentelemetry-exporter-otlp-proto-http (>=1.20.0) ; extra == "otel"
Requires-Dist: opentelemetry-instrumentation-requests (>=0.41b0) ; extra == "otel"
Requires-Dist: packaging (>=24.0,<25.0) ; extra == "gcp"
Project-URL: Documentation, https://docs.metaflow.org
